{
	"abstract" : true,
	"artifacts" : 
	[
		{
			"path" : "/opt/homebrew/lib/libre2.11.0.0.dylib"
		}
	],
	"backtrace" : 9,
	"backtraceGraph" : 
	{
		"commands" : 
		[
			"add_library",
			"include",
			"find_package",
			"set_target_properties"
		],
		"files" : 
		[
			"/opt/homebrew/lib/cmake/re2/re2Targets.cmake",
			"/opt/homebrew/lib/cmake/re2/re2Config.cmake",
			"/opt/homebrew/lib/cmake/grpc/modules/Findre2.cmake",
			"/opt/homebrew/lib/cmake/grpc/gRPCConfig.cmake",
			"CMakeLists.txt"
		],
		"nodes" : 
		[
			{
				"file" : 4
			},
			{
				"command" : 2,
				"file" : 4,
				"line" : 9,
				"parent" : 0
			},
			{
				"file" : 3,
				"parent" : 1
			},
			{
				"command" : 2,
				"file" : 3,
				"line" : 20,
				"parent" : 2
			},
			{
				"file" : 2,
				"parent" : 3
			},
			{
				"command" : 2,
				"file" : 2,
				"line" : 15,
				"parent" : 4
			},
			{
				"file" : 1,
				"parent" : 5
			},
			{
				"command" : 1,
				"file" : 1,
				"line" : 50,
				"parent" : 6
			},
			{
				"file" : 0,
				"parent" : 7
			},
			{
				"command" : 0,
				"file" : 0,
				"line" : 59,
				"parent" : 8
			},
			{
				"command" : 3,
				"file" : 0,
				"line" : 61,
				"parent" : 8
			}
		]
	},
	"codemodelVersion" : 
	{
		"major" : 2,
		"minor" : 9
	},
	"id" : "re2::re2::@6890427a1f51a3e7e1df",
	"imported" : true,
	"interfaceCompileDependencies" : 
	[
		{
			"backtrace" : 10,
			"id" : "Threads::Threads::@6890427a1f51a3e7e1df"
		},
		{
			"backtrace" : 10,
			"id" : "absl::absl_check::@6890427a1f51a3e7e1df"
		},
		{
			"backtrace" : 10,
			"id" : "absl::absl_log::@6890427a1f51a3e7e1df"
		},
		{
			"backtrace" : 10,
			"id" : "absl::base::@6890427a1f51a3e7e1df"
		},
		{
			"backtrace" : 10,
			"id" : "absl::core_headers::@6890427a1f51a3e7e1df"
		},
		{
			"backtrace" : 10,
			"id" : "absl::fixed_array::@6890427a1f51a3e7e1df"
		},
		{
			"backtrace" : 10,
			"id" : "absl::flags::@6890427a1f51a3e7e1df"
		},
		{
			"backtrace" : 10,
			"id" : "absl::flat_hash_map::@6890427a1f51a3e7e1df"
		},
		{
			"backtrace" : 10,
			"id" : "absl::flat_hash_set::@6890427a1f51a3e7e1df"
		},
		{
			"backtrace" : 10,
			"id" : "absl::hash::@6890427a1f51a3e7e1df"
		},
		{
			"backtrace" : 10,
			"id" : "absl::inlined_vector::@6890427a1f51a3e7e1df"
		},
		{
			"backtrace" : 10,
			"id" : "absl::optional::@6890427a1f51a3e7e1df"
		},
		{
			"backtrace" : 10,
			"id" : "absl::span::@6890427a1f51a3e7e1df"
		},
		{
			"backtrace" : 10,
			"id" : "absl::str_format::@6890427a1f51a3e7e1df"
		},
		{
			"backtrace" : 10,
			"id" : "absl::strings::@6890427a1f51a3e7e1df"
		},
		{
			"backtrace" : 10,
			"id" : "absl::synchronization::@6890427a1f51a3e7e1df"
		}
	],
	"interfaceLinkLibraries" : 
	[
		{
			"backtrace" : 10,
			"id" : "Threads::Threads::@6890427a1f51a3e7e1df"
		},
		{
			"backtrace" : 10,
			"id" : "absl::absl_check::@6890427a1f51a3e7e1df"
		},
		{
			"backtrace" : 10,
			"id" : "absl::absl_log::@6890427a1f51a3e7e1df"
		},
		{
			"backtrace" : 10,
			"id" : "absl::base::@6890427a1f51a3e7e1df"
		},
		{
			"backtrace" : 10,
			"id" : "absl::core_headers::@6890427a1f51a3e7e1df"
		},
		{
			"backtrace" : 10,
			"id" : "absl::fixed_array::@6890427a1f51a3e7e1df"
		},
		{
			"backtrace" : 10,
			"id" : "absl::flags::@6890427a1f51a3e7e1df"
		},
		{
			"backtrace" : 10,
			"id" : "absl::flat_hash_map::@6890427a1f51a3e7e1df"
		},
		{
			"backtrace" : 10,
			"id" : "absl::flat_hash_set::@6890427a1f51a3e7e1df"
		},
		{
			"backtrace" : 10,
			"id" : "absl::hash::@6890427a1f51a3e7e1df"
		},
		{
			"backtrace" : 10,
			"id" : "absl::inlined_vector::@6890427a1f51a3e7e1df"
		},
		{
			"backtrace" : 10,
			"id" : "absl::optional::@6890427a1f51a3e7e1df"
		},
		{
			"backtrace" : 10,
			"id" : "absl::span::@6890427a1f51a3e7e1df"
		},
		{
			"backtrace" : 10,
			"id" : "absl::str_format::@6890427a1f51a3e7e1df"
		},
		{
			"backtrace" : 10,
			"id" : "absl::strings::@6890427a1f51a3e7e1df"
		},
		{
			"backtrace" : 10,
			"id" : "absl::synchronization::@6890427a1f51a3e7e1df"
		}
	],
	"local" : true,
	"name" : "re2::re2",
	"nameOnDisk" : "libre2.11.0.0.dylib",
	"paths" : 
	{
		"build" : ".",
		"source" : "."
	},
	"sources" : [],
	"type" : "SHARED_LIBRARY"
}
